nonebot_plugin_userinfo/__init__.py
nonebot_plugin_userinfo/adapters/__init__.py
nonebot_plugin_userinfo/adapters/console.py
nonebot_plugin_userinfo/adapters/discord.py
nonebot_plugin_userinfo/adapters/dodo.py
nonebot_plugin_userinfo/adapters/feishu.py
nonebot_plugin_userinfo/adapters/kaiheila.py
nonebot_plugin_userinfo/adapters/onebot_v11.py
nonebot_plugin_userinfo/adapters/onebot_v12.py
nonebot_plugin_userinfo/adapters/qq.py
nonebot_plugin_userinfo/adapters/red.py
nonebot_plugin_userinfo/adapters/satori.py
nonebot_plugin_userinfo/adapters/telegram.py
nonebot_plugin_userinfo/exception.py
nonebot_plugin_userinfo/getter.py
nonebot_plugin_userinfo/image_source.py
nonebot_plugin_userinfo/py.typed
nonebot_plugin_userinfo/user_info.py
nonebot_plugin_userinfo/utils.py
nonebot_plugin_userinfo-0.2.6.dist-info/LICENSE
nonebot_plugin_userinfo-0.2.6.dist-info/METADATA
nonebot_plugin_userinfo-0.2.6.dist-info/WHEEL
nonebot_plugin_userinfo-0.2.6.dist-info/RECORD
