Metadata-Version: 2.1
Name: nonebot_plugin_userinfo
Version: 0.2.6
Summary: Nonebot2 用户信息获取插件
Home-page: https://github.com/noneplugin/nonebot-plugin-userinfo
License: MIT
Author: meetwq
Author-email: meetwq@gmail.com
Requires-Python: >=3.9,<4.0
Classifier: License :: OSI Approved :: MIT License
Classifier: Programming Language :: Python :: 3
Classifier: Programming Language :: Python :: 3.9
Classifier: Programming Language :: Python :: 3.10
Classifier: Programming Language :: Python :: 3.11
Classifier: Programming Language :: Python :: 3.12
Requires-Dist: cachetools (>=5.0.0,<6.0.0)
Requires-Dist: emoji (>=2.0.0,<3.0.0)
Requires-Dist: httpx (>=0.20.0,<1.0.0)
Requires-Dist: nonebot2 (>=2.3.0,<3.0.0)
Requires-Dist: strenum (>=0.4.15,<0.5.0)
Project-URL: Repository, https://github.com/noneplugin/nonebot-plugin-userinfo
